chimborazo/__init__.py
chimborazo/main.py
chimborazo-0.1.0.dist-info/WHEEL
chimborazo-0.1.0.dist-info/METADATA
chimborazo-0.1.0.dist-info/RECORD
